durables/__init__.py
durables/durable_functions.py
durables/models.py
durables/persistence/jsonl.py
durables/persistence/nats.py
durables/persistence/protocol.py
durables/persistence/utils.py
durables-0.1.0.dist-info/METADATA
durables-0.1.0.dist-info/WHEEL
durables-0.1.0.dist-info/RECORD
