Metadata-Version: 2.4
Name: durables
Version: 0.1.0
Summary: A lightweight durable functions framework with different persistence layers.
Requires-Python: >=3.12
Requires-Dist: dill>=0.3.9
Requires-Dist: nats-py>=2.10.0
Requires-Dist: pydantic>=2.10.6
Requires-Dist: watchdog>=6.0.0
